{"authorDailyContributionsMap":{"DaneMarc":[],"TypeDefinition":[{"date":"2022-03-02","commitResults":[{"hash":"1f68fc95c9a6eaaba079a7a1050a2d26e9c49376","messageTitle":"Make person fields more modular.","messageBody":"","fileTypesAndContributionMap":{"functional-code":{"insertions":134,"deletions":49},"other":{"insertions":1,"deletions":1},"docs":{"insertions":2,"deletions":2},"test-code":{"insertions":4,"deletions":4}}},{"hash":"29c9661f870ee28b4740bdd892969ae4330351c3","messageTitle":"Fix checkstyle issues","messageBody":"","fileTypesAndContributionMap":{"functional-code":{"insertions":24,"deletions":7}}},{"hash":"e4d6a5b16f3290894e005db936cdb7edee60f3d8","messageTitle":"Fix checkstyle issues","messageBody":"","fileTypesAndContributionMap":{"functional-code":{"insertions":21,"deletions":15}}},{"hash":"d190e24564dd30312bd7f6cf3de182195bf55cac","messageTitle":"Fix test case failure","messageBody":"","fileTypesAndContributionMap":{"functional-code":{"insertions":7,"deletions":5}}},{"hash":"ff4fef8623a27c685b8546beab904a663d54b7dd","messageTitle":"Fix issues as pointed out in PR #16","messageBody":"","fileTypesAndContributionMap":{"functional-code":{"insertions":18,"deletions":4}}},{"hash":"b317b8b4a1df8f6d056780ca50e2444201c254d6","messageTitle":"Fix checkstyle issues","messageBody":"","fileTypesAndContributionMap":{"functional-code":{"insertions":1,"deletions":1}}}]}],"LapisRaider":[{"date":"2022-03-01","commitResults":[{"hash":"b2af33e1c3c5a41479456fec6e37a12d17183289","messageTitle":"Dummy commit","messageBody":"Triggers CI to confirm CI is able to upload generated coverage data to CodeCov.","fileTypesAndContributionMap":{"docs":{"insertions":1,"deletions":0}}},{"hash":"af40671357e166e8fca239992bf2eb3ead2eaf22","messageTitle":"Update Readme to have Codecov badge","messageBody":"","fileTypesAndContributionMap":{"docs":{"insertions":1,"deletions":0}}},{"hash":"2af6bca42d339ca043c4e73e72e29f3478036519","messageTitle":"Update README.md","messageBody":"","fileTypesAndContributionMap":{"docs":{"insertions":0,"deletions":1}}}]}],"zunedz":[],"KeithCZW":[]},"authorFileTypeContributionMap":{"DaneMarc":{"docs":0,"functional-code":0,"test-code":0},"TypeDefinition":{"docs":2,"functional-code":175,"test-code":4},"LapisRaider":{"docs":2,"functional-code":0,"test-code":0},"zunedz":{"docs":0,"functional-code":0,"test-code":0},"KeithCZW":{"docs":0,"functional-code":0,"test-code":0}},"authorContributionVariance":{"DaneMarc":0.0,"TypeDefinition":6390.5317,"LapisRaider":0.6390533,"zunedz":0.0,"KeithCZW":0.0},"authorDisplayNameMap":{"DaneMarc":"CS2103T-W09-2 DANE..ISAN","TypeDefinition":"CS2103T-W09-2 LIM ..ERRY","LapisRaider":"CS2103T-W09-2 LIM ..NGIE","zunedz":"CS2103T-W09-2 DAFF..DILA","KeithCZW":"CS2103T-W09-2 CHEN..EITH"}}
